NetMet/__init__.py
NetMet/_savdata.py
NetMet/app.py
NetMet/config.py
NetMet/encrypt.py
NetMet/myipfakes.py
NetMet/requests_html.py
NetMet-1.0.3.dist-info/LICENSE.txt
NetMet-1.0.3.dist-info/METADATA
NetMet-1.0.3.dist-info/WHEEL
NetMet-1.0.3.dist-info/top_level.txt
NetMet-1.0.3.dist-info/RECORD
