Metadata-Version: 2.1
Name: NetMet
Version: 1.0.3
Summary: UNKNOWN
Home-page: https://github.com/LcfherShell/NetMet.git
Author: alfiandecker2
Author-email: <lcfhershell@tutanota.com>
License: MIT
Keywords: MITM,Manipulate,IPAddress,Network-Calculate,NetMet,PyNews,PyWeathers
Platform: UNKNOWN
Classifier: Development Status :: 1 - Planning
Classifier: Intended Audience :: Developers
Classifier: License :: OSI Approved :: MIT License
Classifier: Programming Language :: Cython
Classifier: Programming Language :: Python
Classifier: Operating System :: MacOS
Classifier: Operating System :: POSIX
Classifier: Operating System :: Unix
Classifier: Operating System :: Microsoft :: Windows
Requires-Python: >=2.6, !=3.0.*, !=3.1.*, !=3.2.*, !=3.3.*, <4
License-File: LICENSE.txt
